fastcli_autocomplete/__init__.py
fastcli_autocomplete/autocomplete.py
fastcli_autocomplete/command_parser.py
fastcli_autocomplete/updater.py
fastcli_autocomplete/utils.py
fastcli_autocomplete-0.1.0.dist-info/METADATA
fastcli_autocomplete-0.1.0.dist-info/WHEEL
fastcli_autocomplete-0.1.0.dist-info/entry_points.txt
fastcli_autocomplete-0.1.0.dist-info/top_level.txt
fastcli_autocomplete-0.1.0.dist-info/RECORD
