Metadata-Version: 2.2
Name: fastcli_autocomplete
Version: 0.1.0
Summary: A Python package to enhance CLI autocomplete performance
Home-page: https://github.com/highspeed8/fastcli_autocomplete
Author: wangfu
Author-email: wangfu0811@gmail.com
Classifier: Programming Language :: Python :: 3
Classifier: License :: OSI Approved :: MIT License
Classifier: Operating System :: OS Independent
Requires-Python: >=3.6
Dynamic: author
Dynamic: author-email
Dynamic: classifier
Dynamic: description-content-type
Dynamic: home-page
Dynamic: requires-python
Dynamic: summary
